raek_mne/__init__.py
raek_mne/raek_mne.py
raek_mne-2022.11.1.dist-info/AUTHORS.rst
raek_mne-2022.11.1.dist-info/LICENSE
raek_mne-2022.11.1.dist-info/METADATA
raek_mne-2022.11.1.dist-info/WHEEL
raek_mne-2022.11.1.dist-info/top_level.txt
raek_mne-2022.11.1.dist-info/RECORD
