Metadata-Version: 2.1
Name: raek-mne
Version: 2022.11.1
Summary: Tools for processing EEG data with MNE.
Home-page: https://github.com/Eklund89/raek_mne
Author: Rasmus Eklund
Author-email: rasmus.eklund@psychology.su.se
License: MIT license
Keywords: raek_mne
Classifier: Development Status :: 2 - Pre-Alpha
Classifier: Intended Audience :: Developers
Classifier: License :: OSI Approved :: MIT License
Classifier: Natural Language :: English
Classifier: Programming Language :: Python :: 3
Classifier: Programming Language :: Python :: 3.6
Classifier: Programming Language :: Python :: 3.7
Classifier: Programming Language :: Python :: 3.8
Requires-Python: >=3.6
License-File: LICENSE
License-File: AUTHORS.rst
